<?xml version="1.0" encoding="UTF-8"?>
<!DOCTYPE generatorConfiguration
        PUBLIC "-//mybatis.org//DTD MyBatis Generator Configuration 1.0//EN"
        "http://mybatis.org/dtd/mybatis-generator-config_1_0.dtd">
<generatorConfiguration>
    <properties resource="generator/generatorConfig.properties"/>
    <!-- 数据库驱动:选择你的本地硬盘上面的数据库驱动包-->
    <classPathEntry location="${mysql.connector.location}"/>
    <context id="DB2Tables"  targetRuntime="MyBatis3">
        <plugin type="org.mybatis.generator.plugins.SerializablePlugin" />
        <plugin type="org.mybatis.generator.plugins.CaseInsensitiveLikePlugin" />
        <plugin type="org.mybatis.generator.plugins.RenameExampleClassPlugin">
            <property name="searchString" value="Example$" />
            <property name="replaceString" value="Conditions" />
        </plugin>
        <commentGenerator>
            <property name="suppressAllComments" value="true" />
        </commentGenerator>

        <jdbcConnection driverClass="com.mysql.jdbc.Driver" connectionURL="${mysql.url}"
            userId="${mysql.user}" password="${mysql.password}" />
            
        <!-- bean -->
        <javaModelGenerator targetPackage="${generator.entity}" targetProject="${generator.targetProject}">
            <property name="enableSubPackages" value="true"/>
            <property name="trimStrings" value="true"/>
        </javaModelGenerator>
        <!-- sql mapper -->
        <sqlMapGenerator targetPackage="${generator.module}" targetProject="${generator.mapperXml}">
            <property name="enableSubPackages" value="true"/>
        </sqlMapGenerator>
        <!-- mapper接口 -->
        <javaClientGenerator type="${generator.type}" targetPackage="${generator.mapper}" targetProject="${generator.targetProject}">
            <property name="enableSubPackages" value="true"/>
        </javaClientGenerator>
        
        <table tableName="tb_file_test" domainObjectName="Test" enableCountByExample="false" enableUpdateByExample="false" enableDeleteByExample="false" enableSelectByExample="false" selectByExampleQueryId="false"></table>
        <!-- 
        <table tableName="tb_file" domainObjectName="TFile" enableCountByExample="false" enableUpdateByExample="false" enableDeleteByExample="false" enableSelectByExample="false" selectByExampleQueryId="false"></table>
        
        <table tableName="tb_file_tree" domainObjectName="FileTree" enableCountByExample="false" enableUpdateByExample="false" enableDeleteByExample="false" enableSelectByExample="false" selectByExampleQueryId="false"></table>
         -->
    </context>
</generatorConfiguration>